<annotation verified="yes">
	<folder>images</folder>
	<filename>usb49.png</filename>
	<path>C:\Users\ngjoh\Google Drive\AFRL\SatelliteSim\pannel\ports\train\images\usb49.png</path>
	<source>
		<database>Unknown</database>
	</source>
	<size>
		<width>2400</width>
		<height>1144</height>
		<depth>3</depth>
	</size>
	<segmented>0</segmented>
	<object>
		<name>usb</name>
		<pose>Unspecified</pose>
		<truncated>0</truncated>
		<difficult>0</difficult>
		<bndbox>
			<xmin>1071</xmin>
			<ymin>476</ymin>
			<xmax>1332</xmax>
			<ymax>700</ymax>
		</bndbox>
	</object>
	<object>
		<name>dc</name>
		<pose>Unspecified</pose>
		<truncated>0</truncated>
		<difficult>0</difficult>
		<bndbox>
			<xmin>1523</xmin>
			<ymin>546</ymin>
			<xmax>1721</xmax>
			<ymax>721</ymax>
		</bndbox>
	</object>
	<object>
		<name>aux</name>
		<pose>Unspecified</pose>
		<truncated>1</truncated>
		<difficult>0</difficult>
		<bndbox>
			<xmin>1801</xmin>
			<ymin>1</ymin>
			<xmax>2167</xmax>
			<ymax>191</ymax>
		</bndbox>
	</object>
</annotation>
